pyshared/__init__.py
pyshared/consts.py
pyshared/crypto.py
pyshared/env.py
pyshared/exceptions.py
pyshared/log.py
pyshared/pytest.py
pyshared/python.py
pyshared/shell.py
pyshared/terminal.py
pyshared/test.py
pyshared/version.py
pyshared-1.6.1.dist-info/LICENSE
pyshared-1.6.1.dist-info/METADATA
pyshared-1.6.1.dist-info/WHEEL
pyshared-1.6.1.dist-info/top_level.txt
pyshared-1.6.1.dist-info/RECORD
