Metadata-Version: 2.1
Name: pyshared
Version: 1.6.1
Summary: A Python library containing common utility functions for use across multiple codebases, filling gaps not covered by the standard Python libraries.
Author-email: Cary Carter <ccarterdev@gmail.com>
License: MIT License
Project-URL: Home, https://github.com/cc-d/PyShared
Project-URL: ChangeLog, https://github.com/cc-d/PyShared/blob/main/CHANGELOG.md
Classifier: Programming Language :: Python :: 3
Classifier: Programming Language :: Python :: 3.7
Classifier: Programming Language :: Python :: 3.8
Classifier: Programming Language :: Python :: 3.9
Classifier: Programming Language :: Python :: 3.10
Classifier: Programming Language :: Python :: 3.11
Classifier: Programming Language :: Python :: 3.12
Classifier: Programming Language :: Python :: Implementation :: CPython
Classifier: License :: OSI Approved :: MIT License
Classifier: Operating System :: OS Independent
Classifier: Development Status :: 3 - Alpha
Classifier: Intended Audience :: Developers
Classifier: Topic :: Software Development :: Libraries :: Python Modules
Classifier: Topic :: Utilities
Classifier: Framework :: Django
Classifier: Framework :: Flask
Classifier: Framework :: Pyramid
Classifier: Framework :: Twisted
Classifier: Environment :: Console
Classifier: Environment :: Web Environment
Classifier: Natural Language :: English
Classifier: Typing :: Typed
Requires-Python: >=3.7
License-File: LICENSE
Provides-Extra: dev
Requires-Dist: pytest ; extra == 'dev'
Requires-Dist: pytest-cov ; extra == 'dev'
Requires-Dist: pytest-mock ; extra == 'dev'
Requires-Dist: black ; extra == 'dev'
Requires-Dist: isort ; extra == 'dev'
Requires-Dist: flake8 ; extra == 'dev'
Requires-Dist: twine ; extra == 'dev'
Requires-Dist: build ; extra == 'dev'
